chatgpt_bot/__init__.py
chatgpt_bot-0.2.1.dist-info/METADATA
chatgpt_bot-0.2.1.dist-info/WHEEL
chatgpt_bot-0.2.1.dist-info/RECORD
