Metadata-Version: 2.1
Name: chatgpt-bot
Version: 0.2.1
Summary: A library that takes the pain out of creating ChatGPT bots.
Home-page: https://github.com/skorokithakis/ChatGPT-Bot
License: MIT
Author: Stavros Korokithakis
Author-email: hi@stavros.io
Requires-Python: >=3.7
Classifier: License :: OSI Approved :: MIT License
Classifier: Programming Language :: Python :: 3
Classifier: Programming Language :: Python :: 3.7
Classifier: Programming Language :: Python :: 3.8
Classifier: Programming Language :: Python :: 3.9
Classifier: Programming Language :: Python :: 3.10
Classifier: Programming Language :: Python :: 3.11
Requires-Dist: openai (>=1.3.5)
Project-URL: Repository, https://github.com/skorokithakis/ChatGPT-Bot
